LICENSE
MANIFEST.in
README.rst
setup.py
bin/notify.py
herald/Client.py
herald/__init__.py
herald.egg-info/PKG-INFO
herald.egg-info/SOURCES.txt
herald.egg-info/dependency_links.txt
herald.egg-info/requires.txt
herald.egg-info/top_level.txt