Metadata-Version: 1.0
Name: herald
Version: 0.4
Summary: Mobile Notifications for Transmission or uTorrent Downloads
Home-page: http://github.com/micahr/herald/
Author: Micah Ransdell
Author-email: mjr578@gmail.com
License: BSD-new
Platform: UNKNOWN
Classifier: Development Status :: 4 - Beta
Classifier: License :: OSI Approved :: BSD License
Classifier: Programming Language :: Python
Classifier: Programming Language :: Python :: 2.5
Classifier: Programming Language :: Python :: 2.6
